napari_help/__init__.py
napari_help/_version.py
napari_help/_widget.py
napari_help/napari.yaml
napari_help/_tests/__init__.py
napari_help/_tests/test_widget.py
napari_help-0.1.0.dist-info/LICENSE
napari_help-0.1.0.dist-info/METADATA
napari_help-0.1.0.dist-info/WHEEL
napari_help-0.1.0.dist-info/entry_points.txt
napari_help-0.1.0.dist-info/top_level.txt
napari_help-0.1.0.dist-info/RECORD
