Metadata-Version: 2.1
Name: napari-help
Version: 0.1.0
Summary: Helpful tooltips for napari.
Home-page: https://github.com/brisvag/napari-help
Author: Lorenzo Gaifas
Author-email: brisvag@gmail.com
License: GPL-3.0
Project-URL: Bug Tracker, https://github.com/brisvag/napari-help/issues
Project-URL: Documentation, https://github.com/brisvag/napari-help#README.md
Project-URL: Source Code, https://github.com/brisvag/napari-help
Project-URL: User Support, https://github.com/brisvag/napari-help/issues
Classifier: Development Status :: 2 - Pre-Alpha
Classifier: Framework :: napari
Classifier: Intended Audience :: Developers
Classifier: License :: OSI Approved :: GNU General Public License v3 (GPLv3)
Classifier: Operating System :: OS Independent
Classifier: Programming Language :: Python
Classifier: Programming Language :: Python :: 3
Classifier: Programming Language :: Python :: 3 :: Only
Classifier: Programming Language :: Python :: 3.8
Classifier: Programming Language :: Python :: 3.9
Classifier: Programming Language :: Python :: 3.10
Classifier: Topic :: Scientific/Engineering :: Image Processing
Requires-Python: >=3.8
License-File: LICENSE
Requires-Dist: napari
Requires-Dist: qtpy
Provides-Extra: testing
Requires-Dist: napari ; extra == 'testing'
Requires-Dist: pyqt5 ; extra == 'testing'
Requires-Dist: pytest ; extra == 'testing'
Requires-Dist: pytest-cov ; extra == 'testing'
Requires-Dist: pytest-qt ; extra == 'testing'
Requires-Dist: tox ; extra == 'testing'
